LICENSE
git_profiles/__about__.py
git_profiles/__init__.py
git_profiles/__main__.py
git_profiles/commands/__init__.py
git_profiles/commands/add_profile.py
git_profiles/commands/base_command.py
git_profiles/commands/current_profile.py
git_profiles/commands/del_profile.py
git_profiles/commands/destroy_profiles.py
git_profiles/commands/list_profiles.py
git_profiles/commands/show_profile.py
git_profiles/commands/update_profile.py
git_profiles/commands/use_profile.py
git_profiles/console/__init__.py
git_profiles/console/executor.py
git_profiles/console/parser.py
git_profiles/git_manager/__init__.py
git_profiles/git_manager/git_manager.py
git_profiles/profile/__init__.py
git_profiles/profile/profile.py
git_profiles/utils/messages.py
git_profiles-1.1.3.dist-info/entry_points.txt
git_profiles-1.1.3.dist-info/LICENSE
git_profiles-1.1.3.dist-info/WHEEL
git_profiles-1.1.3.dist-info/METADATA
git_profiles-1.1.3.dist-info/RECORD
