Metadata-Version: 2.1
Name: git-profiles
Version: 1.1.3
Summary: Python package that helps you easily manage and switch between multiple git profiles.
Home-page: https://github.com/popadi/git-profiles
License: MIT
Keywords: git,profiles,git-profiles,multiple
Author: Adrian Pop
Author-email: popadrian1996@gmail.com
Requires-Python: >=3.6,<4.0
Classifier: Environment :: Console
Classifier: License :: OSI Approved :: MIT License
Classifier: Operating System :: OS Independent
Classifier: Programming Language :: Python :: 3
Classifier: Programming Language :: Python :: 3.6
Classifier: Programming Language :: Python :: 3.7
Classifier: Topic :: Software Development :: Libraries :: Python Modules
Classifier: Topic :: Software Development :: Version Control :: Git
Project-URL: Repository, https://github.com/popadi/git-profiles
